pytle/__init__.py
pytle/cli.py
pytle/version.py
pytle/argsc/__init__.py
pytle/data/sats/AO-7.json
pytle/data/sats/AO-73.json
pytle/data/sats/AO-85.json
pytle/data/sats/AO-91.json
pytle/data/sats/AO-92.json
pytle/data/sats/ARISS.json
pytle/data/sats/CAS-4A.json
pytle/data/sats/CAS-4B.json
pytle/data/sats/FO-29.json
pytle/data/sats/FS-3.json
pytle/data/sats/NO-84.json
pytle/data/sats/SO-50.json
pytle/data/sats/UKUBE-1.json
pytle/data/sats/XW-2A.json
pytle/data/sats/XW-2B.json
pytle/data/sats/XW-2C.json
pytle/data/sats/XW-2D.json
pytle/data/sats/XW-2F.json
pytle/data/sats/__init__.py
pytle/data/templates/__init__.py
pytle/data/templates/sat_freq_table.j2
pytle/data/templates/sat_info.j2
pytle-0.0.3.dist-info/LICENSE
pytle-0.0.3.dist-info/METADATA
pytle-0.0.3.dist-info/WHEEL
pytle-0.0.3.dist-info/entry_points.txt
pytle-0.0.3.dist-info/top_level.txt
pytle-0.0.3.dist-info/RECORD
