Metadata-Version: 2.1
Name: pytle
Version: 0.0.3
Summary: Simple utility and module to download and load TLE information
Home-page: https://github.com/jeremymturner/pytle
Author: Jeremy Turner
Author-email: jeremy@jeremymturner.com
License: Apache
Keywords: hamradio satellites tle
Platform: UNKNOWN
Classifier: Development Status :: 4 - Beta
Classifier: Environment :: Console
Classifier: Intended Audience :: Science/Research
Classifier: Operating System :: OS Independent
Classifier: License :: OSI Approved :: Apache Software License
Classifier: Programming Language :: Python :: 3
Classifier: Programming Language :: Python :: 3.3
Classifier: Programming Language :: Python :: 3.4
Classifier: Programming Language :: Python :: 3.5
Classifier: Programming Language :: Python :: 3.6
Classifier: Programming Language :: Python :: 3.7
Classifier: Programming Language :: Python :: 3.8
Classifier: Programming Language :: Python :: 3.9
Requires-Dist: ephem
Requires-Dist: jinja2
